[
  {
    "id": 1,
    "title": "Luxury Product Reveal",
    "description": "Premium cinematic reveal for beauty, fashion, lifestyle and high-end consumer products.",
    "cover_image": "/assets/images/default-cover.png",
    "preview_video_url": "",
    "industry": "Beauty / Fashion / Lifestyle",
    "style_tags": ["luxury", "cinematic", "product reveal"],
    "duration": "15s",
    "aspect_ratio": "9:16",
    "base_price": "From $499",
    "turnaround": "5-7 days",
    "difficulty": "medium",
    "related_work_id": 0,
    "status": "published",
    "sort_order": 1,
    "created_at": "2026-06-29T00:00:00.000Z",
    "updated_at": "2026-06-29T00:00:00.000Z"
  },
  {
    "id": 2,
    "title": "Social Launch Remix",
    "description": "Fast vertical launch remix for TikTok, Instagram Reels and YouTube Shorts.",
    "cover_image": "/assets/images/default-cover.png",
    "preview_video_url": "",
    "industry": "DTC / Consumer Tech / New Products",
    "style_tags": ["launch", "social", "short ads"],
    "duration": "10-15s",
    "aspect_ratio": "9:16",
    "base_price": "From $399",
    "turnaround": "3-5 days",
    "difficulty": "easy",
    "related_work_id": 0,
    "status": "published",
    "sort_order": 2,
    "created_at": "2026-06-29T00:00:00.000Z",
    "updated_at": "2026-06-29T00:00:00.000Z"
  },
  {
    "id": 3,
    "title": "Surreal Brand Film",
    "description": "A more expressive AI visual direction for brands that need impact, memory and visual storytelling.",
    "cover_image": "/assets/images/default-cover.png",
    "preview_video_url": "",
    "industry": "Brand / Culture / Campaign",
    "style_tags": ["surreal", "brand film", "storytelling"],
    "duration": "30s",
    "aspect_ratio": "16:9 / 9:16",
    "base_price": "From $999",
    "turnaround": "7-14 days",
    "difficulty": "hard",
    "related_work_id": 0,
    "status": "published",
    "sort_order": 3,
    "created_at": "2026-06-29T00:00:00.000Z",
    "updated_at": "2026-06-29T00:00:00.000Z"
  }
]
